image_multi_thresholding/__init__.py
image_multi_thresholding/base.py
image_multi_thresholding/thresholding_windows.py
image_multi_thresholding/utils.py
image_multi_thresholding/threshold/__init__.py
image_multi_thresholding/threshold/abc.py
image_multi_thresholding/threshold/aco.py
image_multi_thresholding/threshold/atc.py
image_multi_thresholding/threshold/deo.py
image_multi_thresholding/threshold/dpc.py
image_multi_thresholding/threshold/gaa.py
image_multi_thresholding/threshold/hca.py
image_multi_thresholding/threshold/hst.py
image_multi_thresholding/threshold/lra.py
image_multi_thresholding/threshold/mcc.py
image_multi_thresholding/threshold/mec.py
image_multi_thresholding/threshold/mll.py
image_multi_thresholding/threshold/otsu.py
image_multi_thresholding/threshold/pso.py
image_multi_thresholding/threshold/sfl.py
image_multi_thresholding/threshold/sta.py
image_multithresholding-1.0.dist-info/LICENSE
image_multithresholding-1.0.dist-info/METADATA
image_multithresholding-1.0.dist-info/WHEEL
image_multithresholding-1.0.dist-info/top_level.txt
image_multithresholding-1.0.dist-info/RECORD
