Metadata-Version: 2.1
Name: image-multithresholding
Version: 1.0
Summary: A Python 3 library to find thresholds in the gray levels histogram of an image.
Home-page: https://github.com/image-multithresholding/Image-multithresholding
Author: Joaquin Leon, Andrea Rey
Author-email: jleon@utn.frba.edu.ar, arey@utn.frba.edu.ar
Project-URL: Bug Tracker, https://github.com/image-multithresholding/Image-multithresholding/issues
Classifier: Programming Language :: Python :: 3
Classifier: License :: OSI Approved :: MIT License
Classifier: Operating System :: OS Independent
Requires-Python: >=3.6
License-File: LICENSE
